[
  {
    "title": "海棠春·已未清明对海棠有赋",
    "author": {
      "name": "吴潜",
      "dynasty": "宋"
    },
    "type": "ancient",
    "content": "海棠亭午沾疏雨。便一饷、胭脂尽吐。老去惜花心，相对花无语。\n羽书万里飞来处。报扫荡、狐嗥兔舞。濯锦古江头，飞景还如许。"
  },
  {
    "title": "遣悲怀三首·其二",
    "author": {
      "name": "元稹",
      "dynasty": "唐"
    },
    "type": "poetry",
    "content": "昔日戏言身后意，今朝都到眼前来。\n衣裳已施行看尽，针线犹存未忍开。\n尚想旧情怜婢仆，也曾因梦送钱财。\n诚知此恨人人有，贫贱夫妻百事哀。"
  },
  {
    "title": "怨",
    "author": {
      "name": "冯小青",
      "dynasty": "明"
    },
    "type": "poetry",
    "content": "新妆竟与画图争，知是昭阳第几名？\n瘦影自临春水照，卿须怜我我怜卿。"
  },
  {
    "title": "己亥岁二首·僖宗广明元年",
    "author": {
      "name": "曹松",
      "dynasty": "唐"
    },
    "type": "poetry",
    "content": "泽国江山入战图，生民何计乐樵苏。\n凭君莫话封侯事，一将功成万骨枯。\n传闻一战百神愁，两岸强兵过未休。\n谁道沧江总无事，近来长共血争流。"
  },
  {
    "title": "梦江南·千万恨",
    "author": {
      "name": "温庭筠",
      "dynasty": "唐"
    },
    "type": "poetry",
    "content": "千万恨，恨极在天涯。山月不知心里事，水风空落眼前花，摇曳碧云斜。"
  },
  {
    "title": "听弹琴",
    "author": {
      "name": "刘长卿",
      "dynasty": "唐"
    },
    "type": "poetry",
    "content": "泠泠七弦上，静听松风寒。\n古调虽自爱，今人多不弹。"
  },
  {
    "title": "雨晴",
    "author": {
      "name": "王驾",
      "dynasty": "唐"
    },
    "type": "poetry",
    "content": "雨前初见花间蕊，雨后兼无叶里花。\n蛱蝶飞来过墙去，却疑春色在邻家。\n雨前初见花间蕊，雨后全无叶底花。\n蜂蝶纷纷过墙去，却疑春色在邻家。"
  },
  {
    "title": "早春呈水部张十八员外二首",
    "author": {
      "name": "韩愈",
      "dynasty": "唐"
    },
    "type": "poetry",
    "content": "天街小雨润如酥，草色遥看近却无。\n最是一年春好处，绝胜烟柳满皇都。\n莫道官忙身老大，即无年少逐春心。\n凭君先到江头看，柳色如今深未深。"
  },
  {
    "title": "咏早梅",
    "author": {
      "name": "何逊",
      "dynasty": "南北朝"
    },
    "type": "poetry",
    "content": "兔园标物序，惊时最是梅。\n衔霜当路发，映雪拟寒开。\n枝横却月观，花绕凌风台。\n朝洒长门泣，夕驻临邛杯。\n应知早飘落，故逐上春来。"
  },
  {
    "title": "天仙子·水调数声持酒听",
    "author": {
      "name": "张先",
      "dynasty": "宋"
    },
    "type": "ancient",
    "content": "水调数声持酒听，午醉醒来愁未醒。送春春去几时回？临晚镜，伤流景，往事后期空记省。\n沙上并禽池上暝，云破月来花弄影。重重帘幕密遮灯，风不定，人初静，明日落红应满径。"
  },
  {
    "title": "凉州词",
    "author": {
      "name": "孟浩然",
      "dynasty": "唐"
    },
    "type": "poetry",
    "content": "浑成紫檀金屑文，作得琵琶声入云。\n胡地迢迢三万里，那堪马上送明君。\n异方之乐令人悲，羌笛胡笳不用吹。\n坐看今夜关山月，思杀边城游侠儿。"
  },
  {
    "title": "积雨辋川庄作",
    "author": {
      "name": "王维",
      "dynasty": "唐"
    },
    "type": "poetry",
    "content": "积雨空林烟火迟，蒸藜炊黍饷东菑。\n漠漠水田飞白鹭，阴阴夏木啭黄鹂。\n山中习静观朝槿，松下清斋折露葵。\n野老与人争席罢，海鸥何事更相疑。"
  },
  {
    "title": "卜算子·答施",
    "author": {
      "name": "乐婉",
      "dynasty": "宋"
    },
    "type": "poetry",
    "content": "相思似海深，旧事如天远。泪滴千千万万行，更使人、愁肠断。\n要见无因见，拼了终难拼。若是前生未有缘，待重结、来生愿。"
  },
  {
    "title": "点绛唇·闺思",
    "author": {
      "name": "李清照",
      "dynasty": "宋"
    },
    "type": "ancient",
    "content": "寂寞深闺，柔肠一寸愁千缕。惜春春去。几点催花雨。\n倚遍阑干，只是无情绪。人何处。连天衰草，望断归来路。"
  },
  {
    "title": "临江仙·夜登小阁忆洛中旧游",
    "author": {
      "name": "陈与义",
      "dynasty": "宋"
    },
    "type": "ancient",
    "content": "忆昔午桥桥上饮，坐中多是豪英。长沟流月去无声。杏花疏影里，吹笛到天明。\n二十余年如一梦，此身虽在堪惊。闲登小阁看新晴。古今多少事，渔唱起三更。"
  },
  {
    "title": "郊行即事",
    "author": {
      "name": "程颢",
      "dynasty": "宋"
    },
    "type": "poetry",
    "content": "芳原绿野恣行事，春入遥山碧四围。\n兴逐乱红穿柳巷，困临流水坐苔矶。\n莫辞盏酒十分劝，只恐风花一片飞。\n况是清明好天气，不妨游衍莫忘归。"
  },
  {
    "title": "宋定伯捉鬼",
    "author": {
      "name": "干宝",
      "dynasty": "晋"
    },
    "type": "ancient",
    "content": "南阳宋定伯，年少时，夜行逢鬼。问之，鬼言：“我是鬼。”鬼问：“汝复谁？”定伯诳之，言：“我亦鬼。”鬼问：“欲至何所？”答曰：“欲至宛市。”鬼言：“我亦欲至宛市。”遂行。\n数里，鬼言：“步行太亟，可共递相担，何如？”定伯曰：“大善。”鬼便先担定伯数里。鬼言：“卿太重，将非鬼也？”定伯言：“我新鬼，故身重耳。”定伯因复担鬼，鬼略无重。如是再三。定伯复言：“我新鬼，不知有何所畏忌？”鬼答言：“惟不喜人唾。”于是共行。道遇水，定伯令鬼先渡，听之，了然无声音。定伯自渡，漕漼作声。鬼复言：“何以作声？”定伯曰：“新死，不习渡水故耳，勿怪吾也。”\n行欲至宛市，定伯便担鬼著肩上，急持之。鬼大呼，声咋咋然，索下，不复听之。径至宛市中下著地，化为一羊，便卖之恐其变化，唾之。得钱千五百，乃去。于时石崇言：“定伯卖鬼,得钱千五百文。”"
  },
  {
    "title": "墨梅",
    "author": {
      "name": "张嵲",
      "dynasty": "宋"
    },
    "type": "poetry",
    "content": "山边幽谷水边村，曾被疏花断客魂。\n犹恨东风无意思，更吹烟雨暗黄昏。"
  },
  {
    "title": "蒹葭",
    "author": {
      "name": "杜甫",
      "dynasty": "唐"
    },
    "type": "poetry",
    "content": "摧折不自守，秋风吹若何。\n暂时花戴雪，几处叶沉波。\n体弱春风早，丛长夜露多。\n江湖后摇落，亦恐岁蹉跎。"
  },
  {
    "title": "岁暮到家",
    "author": {
      "name": "蒋士铨",
      "dynasty": "清"
    },
    "type": "poetry",
    "content": "爱子心无尽，归家喜及辰。\n寒衣针线密，家信墨痕新。\n见面怜清瘦，呼儿问苦辛。\n低徊愧人子，不敢叹风尘。"
  },
  {
    "title": "终南山",
    "author": {
      "name": "王维",
      "dynasty": "唐"
    },
    "type": "poetry",
    "content": "太乙近天都，连山接海隅。\n白云回望合，青霭入看无。\n分野中峰变，阴晴众壑殊。\n欲投人处宿，隔水问樵夫。"
  },
  {
    "title": "夏夜追凉",
    "author": {
      "name": "杨万里",
      "dynasty": "宋"
    },
    "type": "poetry",
    "content": "夜热依然午热同，开门小立月明中。\n竹深树密虫鸣处，时有微凉不是风。"
  },
  {
    "title": "咏柳",
    "author": {
      "name": "曾巩",
      "dynasty": "宋"
    },
    "type": "poetry",
    "content": "乱条犹未变初黄，倚得东风势便狂。\n解把飞花蒙日月，不知天地有清霜。"
  },
  {
    "title": "送别诗",
    "author": {
      "name": "佚名",
      "dynasty": "隋"
    },
    "type": "poetry",
    "content": "杨柳青青著地垂，杨花漫漫搅天飞。\n柳条折尽花飞尽，借问行人归不归？"
  },
  {
    "title": "东栏梨花",
    "author": {
      "name": "苏轼",
      "dynasty": "宋"
    },
    "type": "poetry",
    "content": "梨花淡白柳深青，柳絮飞时花满城。\n惆怅东栏一株雪，人生看得几清明。"
  },
  {
    "title": "醉赠刘二十八使君",
    "author": {
      "name": "白居易",
      "dynasty": "唐"
    },
    "type": "poetry",
    "content": "为我引杯添酒饮，与君把箸击盘歌。\n诗称国手徒为尔，命压人头不奈何。\n举眼风光长寂寞，满朝官职独蹉跎。\n亦知合被才名折，二十三年折太多。"
  },
  {
    "title": "国风·卫风·淇奥",
    "author": {
      "name": "佚名",
      "dynasty": "先秦"
    },
    "type": "ancient",
    "content": "瞻彼淇奥，绿竹猗猗。有匪君子，如切如磋，如琢如磨。瑟兮僩兮，赫兮咺兮。有匪君子，终不可谖兮。\n瞻彼淇奥，绿竹青青。有匪君子，充耳琇莹，会弁如星。瑟兮僩兮，赫兮咺兮。有匪君子，终不可谖兮。\n瞻彼淇奥，绿竹如箦。有匪君子，如金如锡，如圭如璧。宽兮绰兮，猗重较兮。善戏谑兮，不为虐兮。"
  },
  {
    "title": "晚晴",
    "author": {
      "name": "李商隐",
      "dynasty": "唐"
    },
    "type": "poetry",
    "content": "深居俯夹城，春去夏犹清。\n天意怜幽草，人间重晚晴。\n并添高阁迥，微注小窗明。\n越鸟巢干后，归飞体更轻。"
  },
  {
    "title": "水调歌头·送章德茂大卿使虏",
    "author": {
      "name": "陈亮",
      "dynasty": "宋"
    },
    "type": "ancient",
    "content": "不见南师久，漫说北群空。当场只手，毕竟还我万夫雄。自笑堂堂汉使，得似洋洋河水，依旧只流东？且复穹庐拜，会向藁街逢！\n尧之都，舜之壤，禹之封。于中应有，一个半个耻臣戎！万里腥膻如许，千古英灵安在，磅礴几时通？胡运何须问，赫日自当中！"
  },
  {
    "title": "满庭芳·山抹微云",
    "author": {
      "name": "秦观",
      "dynasty": "宋"
    },
    "type": "poetry",
    "content": "山抹微云，天连衰草，画角声断谯门。暂停征棹，聊共引离尊。多少蓬莱旧事，空回首、烟霭纷纷。斜阳外，寒鸦万点，流水绕孤村。\n销魂。当此际，香囊暗解，罗带轻分。谩赢得、青楼薄幸名存。此去何时见也，襟袖上、空惹啼痕。伤情处，高城望断，灯火已黄昏。"
  },
  {
    "title": "汉江临泛",
    "author": {
      "name": "王维",
      "dynasty": "唐"
    },
    "type": "poetry",
    "content": "楚塞三湘接，荆门九派通。\n江流天地外，山色有无中。\n郡邑浮前浦，波澜动远空。\n襄阳好风日，留醉与山翁。"
  },
  {
    "title": "竹枝词·山桃红花满上头",
    "author": {
      "name": "刘禹锡",
      "dynasty": "唐"
    },
    "type": "poetry",
    "content": "山桃红花满上头，蜀江春水拍山流。\n花红易衰似郎意，水流无限似侬愁。"
  },
  {
    "title": "丰乐亭游春·其三",
    "author": {
      "name": "欧阳修",
      "dynasty": "宋"
    },
    "type": "poetry",
    "content": "红树青山日欲斜，长郊草色绿无涯。\n游人不管春将老，来往亭前踏落花。"
  },
  {
    "title": "临江仙·梅",
    "author": {
      "name": "李清照",
      "dynasty": "宋"
    },
    "type": "ancient",
    "content": "庭院深深深几许，云窗雾阁春迟。为谁憔悴损芳姿。夜来清梦好，应是发南枝。\n玉瘦檀轻无限恨，南楼羌管休吹。浓香吹尽有谁知。暖风迟日也，别到杏花肥。"
  },
  {
    "title": "李白墓",
    "author": {
      "name": "白居易",
      "dynasty": "唐"
    },
    "type": "poetry",
    "content": "采石江边李白坟，绕田无限草连云。\n可怜荒垄穷泉骨，曾有惊天动地文。\n但是诗人多薄命，就中沦落不过君。"
  },
  {
    "title": "春兴",
    "author": {
      "name": "武元衡",
      "dynasty": "唐"
    },
    "type": "poetry",
    "content": "杨柳阴阴细雨晴，残花落尽见流莺。\n春风一夜吹乡梦，又逐春风到洛城。"
  },
  {
    "title": "永遇乐·落日熔金",
    "author": {
      "name": "李清照",
      "dynasty": "宋"
    },
    "type": "poetry",
    "content": "落日熔金，暮云合璧，人在何处。染柳烟浓，吹梅笛怨，春意知几许。元宵佳节，融和天气，次第岂无风雨。来相召、香车宝马，谢他酒朋诗侣。\n中州盛日，闺门多暇，记得偏重三五。铺翠冠儿，捻金雪柳，簇带争济楚。如今憔悴，风鬟霜鬓，怕见夜间出去。不如向、帘儿底下，听人笑语。"
  },
  {
    "title": "长安秋望",
    "author": {
      "name": "杜牧",
      "dynasty": "唐"
    },
    "type": "poetry",
    "content": "楼倚霜树外，镜天无一毫。\n南山与秋色，气势两相高。"
  },
  {
    "title": "国风·召南·鹊巢",
    "author": {
      "name": "佚名",
      "dynasty": "先秦"
    },
    "type": "poetry",
    "content": "维鹊有巢，维鸠居之。之子于归，百两御之。\n维鹊有巢，维鸠方之。之子于归，百两将之。\n维鹊有巢，维鸠盈之。之子于归，百两成之。"
  },
  {
    "title": "浣溪沙·淡荡春光寒食天",
    "author": {
      "name": "李清照",
      "dynasty": "宋"
    },
    "type": "poetry",
    "content": "淡荡春光寒食天，玉炉沉水袅残烟。梦回山枕隐花钿。\n海燕未来人斗草，江梅已过柳生绵。黄昏疏雨湿秋千。"
  },
  {
    "title": "于易水送人",
    "author": {
      "name": "骆宾王",
      "dynasty": "唐"
    },
    "type": "poetry",
    "content": "此地别燕丹，壮士发冲冠。\n昔时人已没，今日水犹寒。"
  },
  {
    "title": "西江月·顷在黄州",
    "author": {
      "name": "苏轼",
      "dynasty": "宋"
    },
    "type": "poetry",
    "foreword": "顷在黄州，春夜行蕲水中，过酒家饮，酒醉，乘月至一溪桥上，解鞍，由肱醉卧少休。及觉已晓，乱山攒拥，流水锵然，疑非尘世也。书此语桥柱上。",
    "content": "照野弥弥浅浪，横空隐隐层霄。障泥未解玉骢骄，我欲醉眠芳草。\n可惜一溪风月，莫教踏碎琼瑶。解鞍欹枕绿杨桥，杜宇一声春晓。"
  },
  {
    "title": "题龙阳县青草湖",
    "author": {
      "name": "唐珙",
      "dynasty": "元"
    },
    "type": "poetry",
    "content": "西风吹老洞庭波，一夜湘君白发多。\n醉后不知天在水，满船清梦压星河。"
  },
  {
    "title": "伐檀",
    "author": {
      "name": "佚名",
      "dynasty": "先秦"
    },
    "type": "ancient",
    "content": "坎坎伐檀兮，置之河之干兮。河水清且涟猗。不稼不穑，胡取禾三百廛兮？不狩不猎，胡瞻尔庭有县貆兮？彼君子兮，不素餐兮！\n坎坎伐辐兮，置之河之侧兮。河水清且直猗。不稼不穑，胡取禾三百亿兮？不狩不猎，胡瞻尔庭有县特兮？彼君子兮，不素食兮！\n坎坎伐轮兮，置之河之漘兮。河水清且沦猗。不稼不穑，胡取禾三百囷兮？不狩不猎，胡瞻尔庭有县鹑兮？彼君子兮，不素飧兮！"
  },
  {
    "title": "邴原泣学",
    "author": {
      "name": "礼赞",
      "dynasty": "明"
    },
    "type": "ancient",
    "content": "邴原少孤，数岁时，过书舍而泣。师曰：“童子何泣？”原曰：“孤者易伤，贫者易感。夫书者，凡得学者，有亲也。一则愿其不孤，二则羡其得学，中心伤感，故泣耳。”师恻然曰：“欲书可耳!”原曰：“无钱资。”师曰：“童子苟有志,吾徒相教,不求资也。”于是遂就书。一冬之间，诵孝经论语。"
  },
  {
    "title": "国风·周南·兔罝",
    "author": {
      "name": "佚名",
      "dynasty": "先秦"
    },
    "type": "poetry",
    "content": "肃肃兔罝，椓之丁丁。赳赳武夫，公侯干城。\n肃肃兔罝，施于中逵。赳赳武夫，公侯好仇。\n肃肃兔罝，施于中林。赳赳武夫，公侯腹心。"
  },
  {
    "title": "蝶恋花·阅尽天涯离别苦",
    "author": {
      "name": "王国维",
      "dynasty": "清"
    },
    "type": "ancient",
    "content": "阅尽天涯离别苦，不道归来，零落花如许。花底相看无一语，绿窗春与天俱莫。\n待把相思灯下诉，一缕新欢，旧恨千千缕。最是人间留不住，朱颜辞镜花辞树。"
  },
  {
    "title": "赴戍登程口占示家人二首",
    "author": {
      "name": "林则徐",
      "dynasty": "清"
    },
    "type": "poetry",
    "content": "出门一笑莫心哀，浩荡襟怀到处开。\n时事难从无过立，达官非自有生来。\n风涛回首空三岛，尘壤从头数九垓。\n休信儿童轻薄语，嗤他赵老送灯台。\n力微任重久神疲，再竭衰庸定不支。\n苟利国家生死以，岂因祸福避趋之。\n谪居正是君恩厚，养拙刚于戍卒宜。\n戏与山妻谈故事，试吟断送老头皮。"
  },
  {
    "title": "辛夷坞",
    "author": {
      "name": "王维",
      "dynasty": "唐"
    },
    "type": "poetry",
    "content": "木末芙蓉花，山中发红萼。\n涧户寂无人，纷纷开且落。"
  },
  {
    "title": "行军九日思长安故园",
    "author": {
      "name": "岑参",
      "dynasty": "唐"
    },
    "type": "poetry",
    "content": "强欲登高去，无人送酒来。\n遥怜故园菊，应傍战场开。"
  }
]